windbg2df/README.MD
windbg2df/__init__.py
windbg2df/requirements.txt
windbg2df/thirdparty.json
windbg2df-0.10.dist-info/LICENSE.rst
windbg2df-0.10.dist-info/METADATA
windbg2df-0.10.dist-info/WHEEL
windbg2df-0.10.dist-info/top_level.txt
windbg2df-0.10.dist-info/RECORD
