Metadata-Version: 2.1
Name: windbg2df
Version: 0.10
Summary: provides a convenient and streamlined approach to analyze Windows processes by converting windbg requests to pandas DataFrames
Home-page: https://github.com/hansalemaos/windbg2df
Author: Johannes Fischer
Author-email: aulasparticularesdealemaosp@gmail.com
License: MIT
Keywords: windbg
Classifier: Development Status :: 4 - Beta
Classifier: Programming Language :: Python :: 3 :: Only
Classifier: Programming Language :: Python :: 3.10
Classifier: Topic :: Software Development :: Libraries :: Python Modules
Classifier: Topic :: Utilities
License-File: LICENSE.rst
Requires-Dist: PyPDump
Requires-Dist: a-pandas-ex-apply-ignore-exceptions
Requires-Dist: ctypes-window-info
Requires-Dist: kthread
Requires-Dist: list-all-files-recursively
Requires-Dist: numexpr
Requires-Dist: numpy
Requires-Dist: pandas
Requires-Dist: regex
Requires-Dist: remtmp
Requires-Dist: taskkill
